<?xml version="1.0" encoding="ISO-8859-1"?>
<?xml-stylesheet type="text/xsl" href="./simple.xsl" ?>
<attrezzo>
	<nome>Carica batterie</nome>
	<marca>PBM</marca>
	<modello>POWERPOINT</modello>
	<anno_fabbricazione></anno_fabbricazione>
	<anno_acquisto>2009</anno_acquisto>
	<matricola>CG0418</matricola>
	<localizzazione>magazzino A</localizzazione>
	<id>21</id>
	<ditta_fabbricatrice>
		<ragionesociale>Pmb Srl</ragionesociale>
		<via>Via Barella</via>
		<citta>Vignola</citta>
		<provincia></provincia>
		<telefono>059-7705311</telefono>
		<fax>059-7705300</fax>
		<mail></mail>
	</ditta_fabbricatrice>
	<ditta_manutentrice>
		<ragionesociale>Colmac Srl</ragionesociale>
		<via>Via Chioda, 76</via>
		<citta>Verona</citta>
		<provincia>VR</provincia>
		<telefono>045-8620924</telefono>
		<fax>045-8620922</fax>
		<mail></mail>
	</ditta_manutentrice>
	<interventi>
		<intervento>
			<manutentore></manutentore>
			<data></data>
			<descrizione>	
			
			</descrizione>
			<fattura>
				<numero></numero>
				<data></data>		
			</fattura>
		</intervento>
	</interventi>
</attrezzo>
